{
  "blogs": [
    {
      "title": "First Blog",
      "body": "lorem ipsum jfhgdskfjh kfjdksjfheskdf fkjshfks fkhgu kghrueoe ehkgrutehu fhdhbgjdbgjkdsgb vdjgd fkdjhgdk jh firueirelir fdkd e oijdl fdjh  kd lkh lfhek ekjhglkdjgldk",
      "author": "mario",
      "id": 1
    },
    {
      "title": "Opening party party!",
      "body": "lorem ipsum jfhgdskfjh kfjdksjfheskdf fkjshfks fkhgu kghrueoe ehkgrutehu fhdhbgjdbgjkdsgb vdjgd fkdjhgdk jh firueirelir fdkd e oijdl fdjh  kd lkh lfhek ekjhglkdjgldk",
      "author": "yoshi",
      "id": 2
    }
  ]
}